whisparr/__init__.py
whisparr/api_client.py
whisparr/api_response.py
whisparr/configuration.py
whisparr/exceptions.py
whisparr/py.typed
whisparr/rest.py
whisparr/api/__init__.py
whisparr/api/alternative_title_api.py
whisparr/api/api_info_api.py
whisparr/api/authentication_api.py
whisparr/api/auto_tagging_api.py
whisparr/api/backup_api.py
whisparr/api/blocklist_api.py
whisparr/api/calendar_api.py
whisparr/api/calendar_feed_api.py
whisparr/api/collection_api.py
whisparr/api/command_api.py
whisparr/api/credit_api.py
whisparr/api/custom_filter_api.py
whisparr/api/custom_format_api.py
whisparr/api/delay_profile_api.py
whisparr/api/disk_space_api.py
whisparr/api/download_client_api.py
whisparr/api/download_client_config_api.py
whisparr/api/extra_file_api.py
whisparr/api/file_system_api.py
whisparr/api/health_api.py
whisparr/api/history_api.py
whisparr/api/host_config_api.py
whisparr/api/import_exclusions_api.py
whisparr/api/import_list_api.py
whisparr/api/import_list_config_api.py
whisparr/api/import_list_movies_api.py
whisparr/api/indexer_api.py
whisparr/api/indexer_config_api.py
whisparr/api/indexer_flag_api.py
whisparr/api/language_api.py
whisparr/api/localization_api.py
whisparr/api/log_api.py
whisparr/api/log_file_api.py
whisparr/api/manual_import_api.py
whisparr/api/media_cover_api.py
whisparr/api/media_management_config_api.py
whisparr/api/metadata_api.py
whisparr/api/metadata_config_api.py
whisparr/api/movie_api.py
whisparr/api/movie_editor_api.py
whisparr/api/movie_file_api.py
whisparr/api/movie_import_api.py
whisparr/api/movie_lookup_api.py
whisparr/api/naming_config_api.py
whisparr/api/notification_api.py
whisparr/api/parse_api.py
whisparr/api/ping_api.py
whisparr/api/quality_definition_api.py
whisparr/api/quality_profile_api.py
whisparr/api/quality_profile_schema_api.py
whisparr/api/queue_action_api.py
whisparr/api/queue_api.py
whisparr/api/queue_details_api.py
whisparr/api/queue_status_api.py
whisparr/api/release_api.py
whisparr/api/release_profile_api.py
whisparr-1.1.1.dist-info/licenses/LICENSE
whisparr-1.1.1.dist-info/METADATA
whisparr-1.1.1.dist-info/WHEEL
whisparr-1.1.1.dist-info/top_level.txt
whisparr-1.1.1.dist-info/RECORD
